Metadata-Version: 2.1
Name: odoo13-addon-l10n-fr-intrastat-product
Version: 13.0.1.0.1.dev8
Summary: DEB (Déclaration d'Échange de Biens) for France
Home-page: https://github.com/OCA/l10n-france
Author: Akretion,Odoo Community Association (OCA)
Author-email: support@odoo-community.org
License: AGPL-3
Platform: UNKNOWN
Classifier: Programming Language :: Python
Classifier: Framework :: Odoo
Classifier: Framework :: Odoo :: 13.0
Classifier: License :: OSI Approved :: GNU Affero General Public License v3
Requires-Python: >=3.5
Requires-Dist: odoo13-addon-intrastat-product
Requires-Dist: odoo13-addon-l10n-fr-department
Requires-Dist: odoo <13.1dev,>=13.0a
